{
  "org.joget.governance.lib.OrphanedFormDataCheck": {
    "status": "WARN",
    "timestamp": 1718100317711,
    "details": [
      {
        "detail": "There are form data tables unused by all apps: \u003cbr/\u003e\u003col\u003e\u003cli\u003eapp_fd_j_user_register\u003c/li\u003e\u003cli\u003eapp_fd_memo\u003c/li\u003e\u003cli\u003eapp_fd_pr_handa_item\u003c/li\u003e\u003cli\u003eapp_fd_travelAdvisory_kary\u003c/li\u003e\u003cli\u003eapp_fd_ptfs_history\u003c/li\u003e\u003cli\u003eapp_fd_j_crm_proposal\u003c/li\u003e\u003cli\u003eapp_fd_j_expense_cat\u003c/li\u003e\u003cli\u003eapp_fd_ptfs_rfa_backup\u003c/li\u003e\u003cli\u003eapp_fd_ptfs_tmp_q\u003c/li\u003e\u003cli\u003eapp_fd_test01\u003c/li\u003e\u003cli\u003eapp_fd_travelAdvisory\u003c/li\u003e\u003cli\u003eapp_fd_j_crm_account\u003c/li\u003e\u003cli\u003eapp_fd_internalMemo\u003c/li\u003e\u003cli\u003eapp_fd_general_approval\u003c/li\u003e\u003cli\u003eapp_fd_ptfs_wschedule_backup\u003c/li\u003e\u003cli\u003eapp_fd_j_isr_remark\u003c/li\u003e\u003cli\u003eapp_fd_ptfs_position_20230810\u003c/li\u003e\u003cli\u003eapp_fd_test_form_01\u003c/li\u003e\u003cli\u003eapp_fd_pur_mst_project_1\u003c/li\u003e\u003cli\u003eapp_fd_general_approvalsign\u003c/li\u003e\u003cli\u003eapp_fd_j_expense_claim\u003c/li\u003e\u003cli\u003eapp_fd_travelAdvisory_loc\u003c/li\u003e\u003cli\u003eapp_fd_assignmentForm\u003c/li\u003e\u003cli\u003eapp_fd_j_isr_request\u003c/li\u003e\u003cli\u003eapp_fd_j_crm_contact\u003c/li\u003e\u003cli\u003eapp_fd_pr_handa\u003c/li\u003e\u003cli\u003eapp_fd_j_expense_approval\u003c/li\u003e\u003cli\u003eapp_fd_j_smtp\u003c/li\u003e\u003cli\u003eapp_fd_j_crm_opportunity\u003c/li\u003e\u003cli\u003eapp_fd_j_temp\u003c/li\u003e\u003cli\u003eapp_fd_j_expense_entry\u003c/li\u003e\u003cli\u003eapp_fd_ptfs_divdepsect\u003c/li\u003e\u003cli\u003eapp_fd_sk_request\u003c/li\u003e\u003cli\u003eapp_fd_appcenter\u003c/li\u003e\u003cli\u003eapp_fd_ptfs_position_temp\u003c/li\u003e\u003cli\u003eapp_fd_ptfs_ou_20210713\u003c/li\u003e\u003cli\u003eapp_fd_ptfs_persarea_20210726\u003c/li\u003e\u003cli\u003eapp_fd_ptfs_position_20220317\u003c/li\u003e\u003c/ol\u003e",
        "suppressed": false
      }
    ],
    "suppressable": true
  },
  "org.joget.governance.lib.ResponseTimesCheck": {
    "status": "PASS",
    "score": 100,
    "timestamp": 1718100342312,
    "suppressable": false
  },
  "lastCheckDate": {
    "status": "FAIL",
    "timestamp": 1718100291305,
    "suppressable": false
  },
  "org.joget.governance.lib.ErrorRateCheck": {
    "status": "PASS",
    "score": 100,
    "timestamp": 1718100291338,
    "details": [
      {
        "detail": "0.00% error rate since last checked",
        "link": "/web/console/monitor/apm",
        "suppressed": false
      }
    ],
    "moreInfo": "\u003ch4\u003eURL:\u003c/h4\u003ehttp://108.137.35.184:8080/jw/web/userview/ptfWorkflow/ptfWorkflow/dept\u003cbr/\u003e",
    "suppressable": false
  },
  "org.joget.governance.lib.SecureProcessesCheck": {
    "status": "FAIL",
    "timestamp": 1718100342319,
    "details": [
      {
        "detail": "App \u003cb\u003ePayment Approval\u003c/b\u003e: Participant “Requester” is not mapped in \u003cb\u003ePayroll\u003c/b\u003e",
        "link": "/web/console/app/paymentApproval/23/process/builder#payroll",
        "appId": "paymentApproval",
        "suppressed": false
      },
      {
        "detail": "App \u003cb\u003ePayment Approval\u003c/b\u003e: Participant “Process Start White List” is not mapped in \u003cb\u003eSend Notification\u003c/b\u003e",
        "link": "/web/console/app/paymentApproval/23/process/builder#sendNotification",
        "appId": "paymentApproval",
        "suppressed": false
      },
      {
        "detail": "App \u003cb\u003ePTF Workflow\u003c/b\u003e: Participant “Approver Comben” is not mapped in \u003cb\u003ePTF\u003c/b\u003e",
        "link": "/web/console/app/ptfWorkflow/52/process/builder#ptf",
        "appId": "ptfWorkflow",
        "suppressed": false
      }
    ],
    "suppressable": true
  },
  "org.joget.governance.lib.SecureAuthenticationCheck": {
    "status": "FAIL",
    "timestamp": 1718100342319,
    "details": [
      {
        "detail": "Security Enhanced Directory Manager is not enabled",
        "suppressed": false
      }
    ],
    "suppressable": false
  },
  "org.joget.governance.lib.EmailUsageCheck": {
    "status": "WARN",
    "timestamp": 1718100291306,
    "details": [
      {
        "detail": "App \u003cb\u003ePayment Approval\u003c/b\u003e: App Variable \u003cb\u003enotifBCC\u003c/b\u003e has following emails used: \u003col\u003e\u003cli\u003edadan.setiadi@itasoft.co.id\u003c/li\u003e\u003c/ol\u003e",
        "link": "/web/console/app/paymentApproval/23/builders",
        "appId": "paymentApproval",
        "suppressed": false
      },
      {
        "detail": "App \u003cb\u003ePayment Approval\u003c/b\u003e: App Variable \u003cb\u003erpaEmail\u003c/b\u003e has following emails used: \u003col\u003e\u003cli\u003edadan.setiadi@itasoft.co.id\u003c/li\u003e\u003c/ol\u003e",
        "link": "/web/console/app/paymentApproval/23/builders",
        "appId": "paymentApproval",
        "suppressed": false
      },
      {
        "detail": "App \u003cb\u003ePayment Approval\u003c/b\u003e: App Variable \u003cb\u003erpaPayrollEmail\u003c/b\u003e has following emails used: \u003col\u003e\u003cli\u003edadan.setiadi@itasoft.co.id\u003c/li\u003e\u003c/ol\u003e",
        "link": "/web/console/app/paymentApproval/23/builders",
        "appId": "paymentApproval",
        "suppressed": false
      },
      {
        "detail": "App \u003cb\u003ePayment Approval\u003c/b\u003e: Process \u003cb\u003epayroll\u003c/b\u003e has following emails used: \u003col\u003e\u003cli\u003enoreply@sinarmasmining.com\u003c/li\u003e\u003c/ol\u003e",
        "link": "/web/console/app/paymentApproval/23/process/builder#payroll",
        "appId": "paymentApproval",
        "suppressed": false
      },
      {
        "detail": "App \u003cb\u003ePayment Approval\u003c/b\u003e: Process \u003cb\u003esendNotification\u003c/b\u003e has following emails used: \u003col\u003e\u003cli\u003enoreply@sinarmasmining.com\u003c/li\u003e\u003cli\u003enoreply@partners97.com\u003c/li\u003e\u003c/ol\u003e",
        "link": "/web/console/app/paymentApproval/23/process/builder#sendNotification",
        "appId": "paymentApproval",
        "suppressed": false
      },
      {
        "detail": "App \u003cb\u003ePTF Workflow\u003c/b\u003e: Form \u003cb\u003e00 - Form PreSubmit\u003c/b\u003e has following emails used: \u003col\u003e\u003cli\u003efalindah.tangketasik@sinarmasmining.com\u003c/li\u003e\u003c/ol\u003e",
        "link": "/web/console/app/ptfWorkflow/52/form/builder/formPreSubmit",
        "appId": "ptfWorkflow",
        "suppressed": false
      },
      {
        "detail": "App \u003cb\u003ePTF Workflow\u003c/b\u003e: Form \u003cb\u003e01 - Form Submit\u003c/b\u003e has following emails used: \u003col\u003e\u003cli\u003ezaenal.muttaqin@sinarmasmining.com\u003c/li\u003e\u003cli\u003efalindah.tangketasik@sinarmasmining.com\u003c/li\u003e\u003c/ol\u003e",
        "link": "/web/console/app/ptfWorkflow/52/form/builder/formSubmit",
        "appId": "ptfWorkflow",
        "suppressed": false
      },
      {
        "detail": "App \u003cb\u003ePTF Workflow\u003c/b\u003e: App Variable \u003cb\u003eadminPAEmail\u003c/b\u003e has following emails used: \u003col\u003e\u003cli\u003eera.hanadila@techconnect.co.id\u003c/li\u003e\u003cli\u003esudaryadi.syahril@techconnect.co.id\u003c/li\u003e\u003cli\u003ehario.prakoso@techconnect.co.id\u003c/li\u003e\u003c/ol\u003e",
        "link": "/web/console/app/ptfWorkflow/52/builders",
        "appId": "ptfWorkflow",
        "suppressed": false
      },
      {
        "detail": "App \u003cb\u003ePTF Workflow\u003c/b\u003e: App Variable \u003cb\u003ebccPTFFullApproved\u003c/b\u003e has following emails used: \u003col\u003e\u003cli\u003ekarina.aswida@techconnect.co.id\u003c/li\u003e\u003cli\u003efalindah.tangketasik@techconnect.co.id\u003c/li\u003e\u003cli\u003eamelia.ganeshanty@techconnect.co.id\u003c/li\u003e\u003c/ol\u003e",
        "link": "/web/console/app/ptfWorkflow/52/builders",
        "appId": "ptfWorkflow",
        "suppressed": false
      },
      {
        "detail": "App \u003cb\u003ePTF Workflow\u003c/b\u003e: App Variable \u003cb\u003eccBuInez\u003c/b\u003e has following emails used: \u003col\u003e\u003cli\u003einnes.margaretha@sinarmasekuritas.co.id\u003c/li\u003e\u003c/ol\u003e",
        "link": "/web/console/app/ptfWorkflow/52/builders",
        "appId": "ptfWorkflow",
        "suppressed": false
      },
      {
        "detail": "App \u003cb\u003ePTF Workflow\u003c/b\u003e: App Variable \u003cb\u003eccIR\u003c/b\u003e has following emails used: \u003col\u003e\u003cli\u003edevvy@beraucoal.co.id\u003c/li\u003e\u003cli\u003edevvy.nurfiyanti@sinarmasmining.com\u003c/li\u003e\u003cli\u003edimas.hendra@beraucoal.co.id\u003c/li\u003e\u003c/ol\u003e",
        "link": "/web/console/app/ptfWorkflow/52/builders",
        "appId": "ptfWorkflow",
        "suppressed": false
      },
      {
        "detail": "App \u003cb\u003ePTF Workflow\u003c/b\u003e: App Variable \u003cb\u003ecombenNotFound\u003c/b\u003e has following emails used: \u003col\u003e\u003cli\u003ejoseph.andreas@sinarmasmining.com\u003c/li\u003e\u003c/ol\u003e",
        "link": "/web/console/app/ptfWorkflow/52/builders",
        "appId": "ptfWorkflow",
        "suppressed": false
      },
      {
        "detail": "App \u003cb\u003ePTF Workflow\u003c/b\u003e: App Variable \u003cb\u003enotifBCC\u003c/b\u003e has following emails used: \u003col\u003e\u003cli\u003ezaenal.muttaqin@techconnect.co.id\u003c/li\u003e\u003c/ol\u003e",
        "link": "/web/console/app/ptfWorkflow/52/builders",
        "appId": "ptfWorkflow",
        "suppressed": false
      },
      {
        "detail": "App \u003cb\u003ePTF Workflow\u003c/b\u003e: App Variable \u003cb\u003epayrollEmail\u003c/b\u003e has following emails used: \u003col\u003e\u003cli\u003eryant.obeng@sinarmasmining.com\u003c/li\u003e\u003cli\u003eendralin.swesy@sinarmasmining.com\u003c/li\u003e\u003cli\u003ecaecilia.frustanti@sinarmasmining.com\u003c/li\u003e\u003cli\u003ebernadus.krisanto@sinarmasmining.com\u003c/li\u003e\u003cli\u003ehandy.aries@techconnect.co.id\u003c/li\u003e\u003c/ol\u003e",
        "link": "/web/console/app/ptfWorkflow/52/builders",
        "appId": "ptfWorkflow",
        "suppressed": false
      },
      {
        "detail": "App \u003cb\u003ePTF Workflow\u003c/b\u003e: App Variable \u003cb\u003erpaCC\u003c/b\u003e has following emails used: \u003col\u003e\u003cli\u003ebramastyo.wicaksono@techconnect.co.id\u003c/li\u003e\u003cli\u003ezaenal.muttaqin@techconnect.co.id\u003c/li\u003e\u003cli\u003ehanda.zaelana@techconnect.co.id\u003c/li\u003e\u003c/ol\u003e",
        "link": "/web/console/app/ptfWorkflow/52/builders",
        "appId": "ptfWorkflow",
        "suppressed": false
      },
      {
        "detail": "App \u003cb\u003ePTF Workflow\u003c/b\u003e: App Variable \u003cb\u003erpaEmail\u003c/b\u003e has following emails used: \u003col\u003e\u003cli\u003erpa1@sinarmasmining.com\u003c/li\u003e\u003c/ol\u003e",
        "link": "/web/console/app/ptfWorkflow/52/builders",
        "appId": "ptfWorkflow",
        "suppressed": false
      },
      {
        "detail": "App \u003cb\u003ePTF Workflow\u003c/b\u003e: App Variable \u003cb\u003erpaEmailNonGroup\u003c/b\u003e has following emails used: \u003col\u003e\u003cli\u003erpa1@partners97.com\u003c/li\u003e\u003c/ol\u003e",
        "link": "/web/console/app/ptfWorkflow/52/builders",
        "appId": "ptfWorkflow",
        "suppressed": false
      },
      {
        "detail": "App \u003cb\u003ePTF Workflow\u003c/b\u003e: Process \u003cb\u003eptf\u003c/b\u003e has following emails used: \u003col\u003e\u003cli\u003enoreply@sinarmasmining.com\u003c/li\u003e\u003cli\u003ejayker85@gmail.com\u003c/li\u003e\u003cli\u003efalindah.tangketasik@partners97.com\u003c/li\u003e\u003cli\u003ebagus.kristian@partners97.com\u003c/li\u003e\u003cli\u003enoreply@partners97.com\u003c/li\u003e\u003c/ol\u003e",
        "link": "/web/console/app/ptfWorkflow/52/process/builder#ptf",
        "appId": "ptfWorkflow",
        "suppressed": false
      },
      {
        "detail": "App \u003cb\u003ePTF Workflow\u003c/b\u003e: Process \u003cb\u003esendNotification\u003c/b\u003e has following emails used: \u003col\u003e\u003cli\u003enoreply@sinarmasmining.com\u003c/li\u003e\u003cli\u003enoreply@partners97.com\u003c/li\u003e\u003c/ol\u003e",
        "link": "/web/console/app/ptfWorkflow/52/process/builder#sendNotification",
        "appId": "ptfWorkflow",
        "suppressed": false
      }
    ],
    "moreInfo": "Emails used in configuration need to be checked to ensure they are not public or unauthorized email addresses.",
    "datas": {
      "appcenter_2": "{\"details\":[],\"timestamp\":1718076065000}",
      "ptfWorkflow_52": "{\"details\":[{\"detail\":\"App \\u003cb\\u003ePTF Workflow\\u003c/b\\u003e: Form \\u003cb\\u003e00 - Form PreSubmit\\u003c/b\\u003e has following emails used: \\u003col\\u003e\\u003cli\\u003efalindah.tangketasik@sinarmasmining.com\\u003c/li\\u003e\\u003c/ol\\u003e\",\"link\":\"/web/console/app/ptfWorkflow/52/form/builder/formPreSubmit\",\"appId\":\"ptfWorkflow\",\"suppressed\":false},{\"detail\":\"App \\u003cb\\u003ePTF Workflow\\u003c/b\\u003e: Form \\u003cb\\u003e01 - Form Submit\\u003c/b\\u003e has following emails used: \\u003col\\u003e\\u003cli\\u003ezaenal.muttaqin@sinarmasmining.com\\u003c/li\\u003e\\u003cli\\u003efalindah.tangketasik@sinarmasmining.com\\u003c/li\\u003e\\u003c/ol\\u003e\",\"link\":\"/web/console/app/ptfWorkflow/52/form/builder/formSubmit\",\"appId\":\"ptfWorkflow\",\"suppressed\":false},{\"detail\":\"App \\u003cb\\u003ePTF Workflow\\u003c/b\\u003e: App Variable \\u003cb\\u003eadminPAEmail\\u003c/b\\u003e has following emails used: \\u003col\\u003e\\u003cli\\u003eera.hanadila@techconnect.co.id\\u003c/li\\u003e\\u003cli\\u003esudaryadi.syahril@techconnect.co.id\\u003c/li\\u003e\\u003cli\\u003ehario.prakoso@techconnect.co.id\\u003c/li\\u003e\\u003c/ol\\u003e\",\"link\":\"/web/console/app/ptfWorkflow/52/builders\",\"appId\":\"ptfWorkflow\",\"suppressed\":false},{\"detail\":\"App \\u003cb\\u003ePTF Workflow\\u003c/b\\u003e: App Variable \\u003cb\\u003ebccPTFFullApproved\\u003c/b\\u003e has following emails used: \\u003col\\u003e\\u003cli\\u003ekarina.aswida@techconnect.co.id\\u003c/li\\u003e\\u003cli\\u003efalindah.tangketasik@techconnect.co.id\\u003c/li\\u003e\\u003cli\\u003eamelia.ganeshanty@techconnect.co.id\\u003c/li\\u003e\\u003c/ol\\u003e\",\"link\":\"/web/console/app/ptfWorkflow/52/builders\",\"appId\":\"ptfWorkflow\",\"suppressed\":false},{\"detail\":\"App \\u003cb\\u003ePTF Workflow\\u003c/b\\u003e: App Variable \\u003cb\\u003eccBuInez\\u003c/b\\u003e has following emails used: \\u003col\\u003e\\u003cli\\u003einnes.margaretha@sinarmasekuritas.co.id\\u003c/li\\u003e\\u003c/ol\\u003e\",\"link\":\"/web/console/app/ptfWorkflow/52/builders\",\"appId\":\"ptfWorkflow\",\"suppressed\":false},{\"detail\":\"App \\u003cb\\u003ePTF Workflow\\u003c/b\\u003e: App Variable \\u003cb\\u003eccIR\\u003c/b\\u003e has following emails used: \\u003col\\u003e\\u003cli\\u003edevvy@beraucoal.co.id\\u003c/li\\u003e\\u003cli\\u003edevvy.nurfiyanti@sinarmasmining.com\\u003c/li\\u003e\\u003cli\\u003edimas.hendra@beraucoal.co.id\\u003c/li\\u003e\\u003c/ol\\u003e\",\"link\":\"/web/console/app/ptfWorkflow/52/builders\",\"appId\":\"ptfWorkflow\",\"suppressed\":false},{\"detail\":\"App \\u003cb\\u003ePTF Workflow\\u003c/b\\u003e: App Variable \\u003cb\\u003ecombenNotFound\\u003c/b\\u003e has following emails used: \\u003col\\u003e\\u003cli\\u003ejoseph.andreas@sinarmasmining.com\\u003c/li\\u003e\\u003c/ol\\u003e\",\"link\":\"/web/console/app/ptfWorkflow/52/builders\",\"appId\":\"ptfWorkflow\",\"suppressed\":false},{\"detail\":\"App \\u003cb\\u003ePTF Workflow\\u003c/b\\u003e: App Variable \\u003cb\\u003enotifBCC\\u003c/b\\u003e has following emails used: \\u003col\\u003e\\u003cli\\u003ezaenal.muttaqin@techconnect.co.id\\u003c/li\\u003e\\u003c/ol\\u003e\",\"link\":\"/web/console/app/ptfWorkflow/52/builders\",\"appId\":\"ptfWorkflow\",\"suppressed\":false},{\"detail\":\"App \\u003cb\\u003ePTF Workflow\\u003c/b\\u003e: App Variable \\u003cb\\u003epayrollEmail\\u003c/b\\u003e has following emails used: \\u003col\\u003e\\u003cli\\u003eryant.obeng@sinarmasmining.com\\u003c/li\\u003e\\u003cli\\u003eendralin.swesy@sinarmasmining.com\\u003c/li\\u003e\\u003cli\\u003ecaecilia.frustanti@sinarmasmining.com\\u003c/li\\u003e\\u003cli\\u003ebernadus.krisanto@sinarmasmining.com\\u003c/li\\u003e\\u003cli\\u003ehandy.aries@techconnect.co.id\\u003c/li\\u003e\\u003c/ol\\u003e\",\"link\":\"/web/console/app/ptfWorkflow/52/builders\",\"appId\":\"ptfWorkflow\",\"suppressed\":false},{\"detail\":\"App \\u003cb\\u003ePTF Workflow\\u003c/b\\u003e: App Variable \\u003cb\\u003erpaCC\\u003c/b\\u003e has following emails used: \\u003col\\u003e\\u003cli\\u003ebramastyo.wicaksono@techconnect.co.id\\u003c/li\\u003e\\u003cli\\u003ezaenal.muttaqin@techconnect.co.id\\u003c/li\\u003e\\u003cli\\u003ehanda.zaelana@techconnect.co.id\\u003c/li\\u003e\\u003c/ol\\u003e\",\"link\":\"/web/console/app/ptfWorkflow/52/builders\",\"appId\":\"ptfWorkflow\",\"suppressed\":false},{\"detail\":\"App \\u003cb\\u003ePTF Workflow\\u003c/b\\u003e: App Variable \\u003cb\\u003erpaEmail\\u003c/b\\u003e has following emails used: \\u003col\\u003e\\u003cli\\u003erpa1@sinarmasmining.com\\u003c/li\\u003e\\u003c/ol\\u003e\",\"link\":\"/web/console/app/ptfWorkflow/52/builders\",\"appId\":\"ptfWorkflow\",\"suppressed\":false},{\"detail\":\"App \\u003cb\\u003ePTF Workflow\\u003c/b\\u003e: App Variable \\u003cb\\u003erpaEmailNonGroup\\u003c/b\\u003e has following emails used: \\u003col\\u003e\\u003cli\\u003erpa1@partners97.com\\u003c/li\\u003e\\u003c/ol\\u003e\",\"link\":\"/web/console/app/ptfWorkflow/52/builders\",\"appId\":\"ptfWorkflow\",\"suppressed\":false},{\"detail\":\"App \\u003cb\\u003ePTF Workflow\\u003c/b\\u003e: Process \\u003cb\\u003eptf\\u003c/b\\u003e has following emails used: \\u003col\\u003e\\u003cli\\u003enoreply@sinarmasmining.com\\u003c/li\\u003e\\u003cli\\u003ejayker85@gmail.com\\u003c/li\\u003e\\u003cli\\u003efalindah.tangketasik@partners97.com\\u003c/li\\u003e\\u003cli\\u003ebagus.kristian@partners97.com\\u003c/li\\u003e\\u003cli\\u003enoreply@partners97.com\\u003c/li\\u003e\\u003c/ol\\u003e\",\"link\":\"/web/console/app/ptfWorkflow/52/process/builder#ptf\",\"appId\":\"ptfWorkflow\",\"suppressed\":false},{\"detail\":\"App \\u003cb\\u003ePTF Workflow\\u003c/b\\u003e: Process \\u003cb\\u003esendNotification\\u003c/b\\u003e has following emails used: \\u003col\\u003e\\u003cli\\u003enoreply@sinarmasmining.com\\u003c/li\\u003e\\u003cli\\u003enoreply@partners97.com\\u003c/li\\u003e\\u003c/ol\\u003e\",\"link\":\"/web/console/app/ptfWorkflow/52/process/builder#sendNotification\",\"appId\":\"ptfWorkflow\",\"suppressed\":false}],\"timestamp\":1717726024000}",
      "paymentApproval_23": "{\"details\":[{\"detail\":\"App \\u003cb\\u003ePayment Approval\\u003c/b\\u003e: App Variable \\u003cb\\u003enotifBCC\\u003c/b\\u003e has following emails used: \\u003col\\u003e\\u003cli\\u003edadan.setiadi@itasoft.co.id\\u003c/li\\u003e\\u003c/ol\\u003e\",\"link\":\"/web/console/app/paymentApproval/23/builders\",\"appId\":\"paymentApproval\",\"suppressed\":false},{\"detail\":\"App \\u003cb\\u003ePayment Approval\\u003c/b\\u003e: App Variable \\u003cb\\u003erpaEmail\\u003c/b\\u003e has following emails used: \\u003col\\u003e\\u003cli\\u003edadan.setiadi@itasoft.co.id\\u003c/li\\u003e\\u003c/ol\\u003e\",\"link\":\"/web/console/app/paymentApproval/23/builders\",\"appId\":\"paymentApproval\",\"suppressed\":false},{\"detail\":\"App \\u003cb\\u003ePayment Approval\\u003c/b\\u003e: App Variable \\u003cb\\u003erpaPayrollEmail\\u003c/b\\u003e has following emails used: \\u003col\\u003e\\u003cli\\u003edadan.setiadi@itasoft.co.id\\u003c/li\\u003e\\u003c/ol\\u003e\",\"link\":\"/web/console/app/paymentApproval/23/builders\",\"appId\":\"paymentApproval\",\"suppressed\":false},{\"detail\":\"App \\u003cb\\u003ePayment Approval\\u003c/b\\u003e: Process \\u003cb\\u003epayroll\\u003c/b\\u003e has following emails used: \\u003col\\u003e\\u003cli\\u003enoreply@sinarmasmining.com\\u003c/li\\u003e\\u003c/ol\\u003e\",\"link\":\"/web/console/app/paymentApproval/23/process/builder#payroll\",\"appId\":\"paymentApproval\",\"suppressed\":false},{\"detail\":\"App \\u003cb\\u003ePayment Approval\\u003c/b\\u003e: Process \\u003cb\\u003esendNotification\\u003c/b\\u003e has following emails used: \\u003col\\u003e\\u003cli\\u003enoreply@sinarmasmining.com\\u003c/li\\u003e\\u003cli\\u003enoreply@partners97.com\\u003c/li\\u003e\\u003c/ol\\u003e\",\"link\":\"/web/console/app/paymentApproval/23/process/builder#sendNotification\",\"appId\":\"paymentApproval\",\"suppressed\":false}],\"timestamp\":1718094789000}"
    },
    "suppressable": true
  },
  "org.joget.governance.lib.CpuUsageCheck": {
    "status": "PASS",
    "score": 94,
    "timestamp": 1718100291305,
    "details": [
      {
        "detail": "Average CPU load at 13.48% for last 10 minutes",
        "link": "/web/console/monitor/apm",
        "suppressed": false
      }
    ],
    "suppressable": false
  },
  "org.joget.governance.lib.DbConnectionsCheck": {
    "status": "PASS",
    "score": 97,
    "timestamp": 1718100291306,
    "details": [
      {
        "detail": "20 DB connections used",
        "suppressed": false
      }
    ],
    "suppressable": false
  },
  "org.joget.governance.lib.MissingPluginCheck": {
    "status": "FAIL",
    "timestamp": 1718100291394,
    "details": [
      {
        "detail": "App \u003cb\u003ePTF Workflow\u003c/b\u003e: Missing plugins found \u003cbr/\u003e\u003col\u003e\u003cli\u003e\u003ca href\u003d\"https://marketplace.joget.org/jw/web/userview/mp/mpp/_/vad?id\u003dajax_selectbox-6.0.0\" target\u003d\"_blank\"\u003eAJAX Select Box Plugin\u003c/a\u003e\u003c/li\u003e\u003c/ol\u003e",
        "link": "/web/console/app/ptfWorkflow/52/builders",
        "appId": "ptfWorkflow",
        "suppressed": false
      },
      {
        "detail": "App \u003cb\u003eJoget User Management Utility for v6\u003c/b\u003e: Missing plugins found \u003cbr/\u003e\u003col\u003e\u003cli\u003eorg.joget.tutorial.JdbcOptionsBinder\u003c/li\u003e\u003c/ol\u003e",
        "link": "/web/console/app/jusermgnt6/1/builders",
        "appId": "jusermgnt6",
        "suppressed": false
      },
      {
        "detail": "App \u003cb\u003eSurat Keputusan\u003c/b\u003e: Missing plugins found \u003cbr/\u003e\u003col\u003e\u003cli\u003e\u003ca href\u003d\"https://marketplace.joget.org/jw/web/userview/mp/mpp/_/vad?id\u003dajax_selectbox-6.0.0\" target\u003d\"_blank\"\u003eAJAX Select Box Plugin\u003c/a\u003e\u003c/li\u003e\u003c/ol\u003e",
        "link": "/web/console/app/suratKeputusan/131/builders",
        "appId": "suratKeputusan",
        "suppressed": false
      }
    ],
    "suppressable": false
  },
  "org.joget.governance.lib.HashVariableCheck": {
    "status": "WARN",
    "timestamp": 1718100291341,
    "details": [
      {
        "detail": "App \u003cb\u003ePayment Approval\u003c/b\u003e: Process \u003cb\u003epayroll\u003c/b\u003e has following unsecure/unescaped Hash Variable used: \u003col\u003e\u003cli\u003e#form.paymentappr_req.nextActivityId#\u003c/li\u003e\u003cli\u003e#envVariable.rpaPayrollEmail#\u003c/li\u003e\u003cli\u003e#form.paymentappr_req.createdBy#\u003c/li\u003e\u003cli\u003e#form.paymentappr_req.createdByName#\u003c/li\u003e\u003cli\u003e#envVariable.rpaEmail#\u003c/li\u003e\u003c/ol\u003e",
        "link": "/web/console/app/paymentApproval/23/process/builder#payroll",
        "appId": "paymentApproval",
        "suppressed": false
      }
    ],
    "moreInfo": "Hash Variable used in SQL and script should escape with \"?sql\", \"?java\" or \"?javascript\".",
    "datas": {
      "appcenter_2": "{\"details\":[],\"timestamp\":1718076065000}",
      "ptfWorkflow_52": "{\"details\":[],\"timestamp\":1717726024000}",
      "paymentApproval_23": "{\"details\":[{\"detail\":\"App \\u003cb\\u003ePayment Approval\\u003c/b\\u003e: Process \\u003cb\\u003epayroll\\u003c/b\\u003e has following unsecure/unescaped Hash Variable used: \\u003col\\u003e\\u003cli\\u003e#form.paymentappr_req.nextActivityId#\\u003c/li\\u003e\\u003cli\\u003e#envVariable.rpaPayrollEmail#\\u003c/li\\u003e\\u003cli\\u003e#form.paymentappr_req.createdBy#\\u003c/li\\u003e\\u003cli\\u003e#form.paymentappr_req.createdByName#\\u003c/li\\u003e\\u003cli\\u003e#envVariable.rpaEmail#\\u003c/li\\u003e\\u003c/ol\\u003e\",\"link\":\"/web/console/app/paymentApproval/23/process/builder#payroll\",\"appId\":\"paymentApproval\",\"suppressed\":false}],\"timestamp\":1718094789000}"
    },
    "suppressable": true
  },
  "org.joget.governance.lib.SecureUserviewsCheck": {
    "status": "FAIL",
    "timestamp": 1718100342415,
    "details": [
      {
        "detail": "App \u003cb\u003ePTF Workflow\u003c/b\u003e: UI \u003cb\u003ePTF Approval\u003c/b\u003e has no permissions configured",
        "link": "/web/console/app/ptfWorkflow/52/userview/builder/ptfWorkflowLog",
        "appId": "ptfWorkflow",
        "suppressed": false
      },
      {
        "detail": "App \u003cb\u003ePTF Workflow\u003c/b\u003e: UI \u003cb\u003ePTF Workflow Report SMMA\u003c/b\u003e has no permissions configured",
        "link": "/web/console/app/ptfWorkflow/52/userview/builder/ptfWorkflowReportSMMA",
        "appId": "ptfWorkflow",
        "suppressed": false
      }
    ],
    "suppressable": true
  },
  "org.joget.governance.lib.MemoryUsageCheck": {
    "status": "PASS",
    "score": 86,
    "timestamp": 1718100291390,
    "details": [
      {
        "detail": "Average free memory available at 54.47% for last 10 minutes",
        "link": "/web/console/monitor/apm",
        "suppressed": false
      }
    ],
    "suppressable": false
  },
  "org.joget.governance.lib.ProcessDataIntegrityCheck": {
    "status": "PASS",
    "timestamp": 1718100342250,
    "suppressable": true
  },
  "org.joget.governance.lib.NamingConventionCheck": {
    "status": "WARN",
    "timestamp": 1718100316232,
    "details": [
      {
        "detail": "App \u003cb\u003ePTF Workflow\u003c/b\u003e: Inconsistent ID case for field ID \u003cb\u003eapproverComBenHead\u003c/b\u003e detected in Form \u003cb\u003e12 - TM Approval\u003c/b\u003e",
        "link": "/web/console/app/ptfWorkflow/52/form/builder/formApproval8",
        "appId": "ptfWorkflow",
        "suppressed": false
      }
    ],
    "suppressable": true
  },
  "org.joget.governance.lib.DeadlineCheckerAvailabilityCheck": {
    "status": "PASS",
    "timestamp": 1718100291306,
    "suppressable": false
  }
}